gdesk/__init__.py
gdesk/__main__.py
gdesk/console.py
gdesk/version.py
gdesk/config/defaults.json
gdesk/config/defaults_unix.json
gdesk/core/__init__.py
gdesk/core/comm.py
gdesk/core/comm_nonduplex.py
gdesk/core/conf.py
gdesk/core/gui_proxy.py
gdesk/core/history.py
gdesk/core/interpreter.py
gdesk/core/shellmod.py
gdesk/core/stdinout.py
gdesk/core/tasks.py
gdesk/core/watcher.py
gdesk/dialogs/__init__.py
gdesk/dialogs/about.py
gdesk/dialogs/base.py
gdesk/dialogs/colormap.py
gdesk/dialogs/editpaths.py
gdesk/dialogs/filedialog.py
gdesk/dialogs/filterlist.py
gdesk/dialogs/formlayout.py
gdesk/dialogs/main.py
gdesk/dialogs/textbrowser.py
gdesk/dicttree/__init__.py
gdesk/dicttree/node.py
gdesk/dicttree/widgets.py
gdesk/external/__init__.py
gdesk/external/channel.py
gdesk/external/client.py
gdesk/ezdock/__init__.py
gdesk/ezdock/boxes.py
gdesk/ezdock/docks.py
gdesk/ezdock/dockwidgets.py
gdesk/ezdock/ezdock.py
gdesk/ezdock/laystruct.py
gdesk/ezdock/overlay.py
gdesk/gcore/__init__.py
gdesk/gcore/guiapp.py
gdesk/gcore/qgc.py
gdesk/gcore/threadcom.py
gdesk/gcore/utils.py
gdesk/graphics/__init__.py
gdesk/graphics/functions.py
gdesk/graphics/grid.py
gdesk/graphics/items.py
gdesk/graphics/plotview.py
gdesk/graphics/point.py
gdesk/graphics/rulers.py
gdesk/graphics/view.py
gdesk/install/__init__.py
gdesk/install/freedesktop.py
gdesk/live/__init__.py
gdesk/live/__main__.py
gdesk/live/__version__.py
gdesk/live/completer.py
gdesk/live/console.py
gdesk/live/interactive.py
gdesk/live/manage.py
gdesk/matplotbe/__init__.py
gdesk/panels/__init__.py
gdesk/panels/base.py
gdesk/panels/panels.py
gdesk/panels/window.py
gdesk/panels/cmdhist/__init__.py
gdesk/panels/cmdhist/panel.py
gdesk/panels/cmdhist/proxy.py
gdesk/panels/console/__init__.py
gdesk/panels/console/consolepanel.py
gdesk/panels/console/consoleproxy.py
gdesk/panels/dialog/__init__.py
gdesk/panels/dialog/proxy.py
gdesk/panels/html/__init__.py
gdesk/panels/html/panel.py
gdesk/panels/html/proxy.py
gdesk/panels/imgview/__init__.py
gamma_desk-1.9.3.dist-info/entry_points.txt
gamma_desk-1.9.3.dist-info/licenses/LICENSE
gamma_desk-1.9.3.dist-info/WHEEL
gamma_desk-1.9.3.dist-info/METADATA
gamma_desk-1.9.3.dist-info/RECORD
