Metadata-Version: 2.4
Name: gamma-desk
Version: 1.9.3
Summary: A Python work environment with image viewers & plots
Author-email: Thomas Cools <thomas.cools@telenet.be>
Requires-Python: >=3.8
Classifier: License :: OSI Approved :: Apache Software License
Classifier: Programming Language :: Python
Classifier: Programming Language :: Python :: 3
Classifier: Programming Language :: Python :: 3.8
Classifier: Programming Language :: Python :: 3.9
Classifier: Programming Language :: Python :: 3.10
Classifier: Programming Language :: Python :: 3.11
Classifier: Programming Language :: Python :: 3.12
Classifier: Programming Language :: Python :: 3.13
License-File: LICENSE
Requires-Dist: pillow
Requires-Dist: imageio
Requires-Dist: imageio-ffmpeg
Requires-Dist: scipy
Requires-Dist: qtpy
Requires-Dist: psutil
Requires-Dist: numba
Requires-Dist: pyzmq
Requires-Dist: packaging
Requires-Dist: matplotlib != 3.5.2
Requires-Dist: legacy-cgi; python_version > '3.12'
Requires-Dist: pywinpty<2.0.15; sys_platform=='win32' and python_version<='3.8'
Requires-Dist: pywinpty; sys_platform=='win32' and python_version>'3.8'
Requires-Dist: pyside6<=6.7; python_version=='3.11'
Requires-Dist: pyside6>=6.8.1; python_version>='3.12'
Requires-Dist: numpy<2; python_version<'3.12'
Requires-Dist: numpy>=2; python_version>='3.12'
Requires-Dist: pyqt6 ; extra == "pyqt6"
Requires-Dist: pyside2 ; extra == "pyside2" and ( python_version<='3.10')
Requires-Dist: pyside6 ; extra == "pyside6" and ( python_version<='3.10')
Project-URL: Source, https://github.com/thocoo/gamma-desk
Provides-Extra: pyqt6
Provides-Extra: pyside2
Provides-Extra: pyside6
